jupswapper/__init__.py
jupswapper/await_confirmation.py
jupswapper/client.py
jupswapper/key.py
jupswapper/logger.py
jupswapper/mints.py
jupswapper/quote.py
jupswapper/send_transaction.py
jupswapper/sign.py
jupswapper/sol_balance.py
jupswapper/swap.py
jupswapper/swap_model.py
jupswapper/token.py
jupswapper/helius/__init__.py
jupswapper/helius/endpoint.py
jupswapper/helius/transaction.py
jupswapper/helius/wallet.py
jupswapper-0.1.1.dist-info/METADATA
jupswapper-0.1.1.dist-info/WHEEL
jupswapper-0.1.1.dist-info/RECORD
