Metadata-Version: 2.3
Name: jupswapper
Version: 0.1.1
Summary: A Python package for token swapping and wallet interactions on Solana using Jupiter Aggregator
Project-URL: Homepage, https://github.com/laroccacharly/jupswap
Author: Charly Robinson La Rocca
Classifier: Development Status :: 3 - Alpha
Classifier: Intended Audience :: Developers
Classifier: License :: OSI Approved :: MIT License
Classifier: Programming Language :: Python :: 3
Classifier: Programming Language :: Python :: 3.12
Requires-Python: >=3.12
Requires-Dist: base58
Requires-Dist: mnemonic
Requires-Dist: pydantic
Requires-Dist: requests
Requires-Dist: solana>=0.35
Requires-Dist: solders
